{
   "markers" : [
      {
         "pin" : "carriergreen",
         "text" : "WP9 and POI 1 /nThuechoea ZE-A g0 \n(DSSA Shepard's Dream - Brothers And Sisters Of The Void)",
         "x" :  -26997.03125,
         "y" :  -48.75,
         "z" : 53262.78125
      },
	  {
         "pin" : "carriergreen",
         "text" : "POI 2 /nFlyoo Groa SO-Z e0 \n(DSSA Solsen’s Alastor \nNSP Solon Trees",
         "x" : -26482.4375,
         "y" : -78.78125,
         "z" : 50335.125
      },
	  {
         "pin" : "green",
         "text" : "POI 3 /nFlyoo Groa XW-W c4-13 \n NSP Solon Trees, Solon Pods and Ice Crystals",
         "x" :   -26476.0625,
         "y" :   -75.75,
         "z" : 50341.8125
      },
	  {
         "pin" : "green",
         "text" : "POI 4 /nEactaisky IR-N e6-2 \n(Eactaisky Stellar Remnant)",
         "x" :  -19483.84375,
         "y" :  8,
         "z" : 43610.375
      },
	  {
         "pin" : "green",
         "text" : "WP10 and POI 5 /nTrignai MT-Q e5-28 \n(Trignai Blend)",
         "x" :  -16355.875,
         "y" :  -70.25,
         "z" : 40895.34375
      }

   ]
}
